ncmirtools/mpidir.py
ncmirtools/__init__.py
ncmirtools/ciluploader.py
ncmirtools/lookup.py
ncmirtools/imagetokiosk.py
ncmirtools/projectsearch.py
ncmirtools/config.py
ncmirtools/mpidinfo.py
ncmirtools/projectdir.py
ncmirtools/ncmirtool.py
ncmirtools/kiosk/__init__.py
ncmirtools/kiosk/transfer.py
ncmirtools/kiosk/datafinder.py
ncmirtools-0.5.2.dist-info/metadata.json
ncmirtools-0.5.2.dist-info/METADATA
ncmirtools-0.5.2.dist-info/DESCRIPTION.rst
ncmirtools-0.5.2.dist-info/WHEEL
ncmirtools-0.5.2.dist-info/top_level.txt
ncmirtools-0.5.2.dist-info/RECORD
ncmirtools-0.5.2.data/scripts/mpidir.py
ncmirtools-0.5.2.data/scripts/imagetokiosk.py
ncmirtools-0.5.2.data/scripts/projectsearch.py
ncmirtools-0.5.2.data/scripts/mpidinfo.py
ncmirtools-0.5.2.data/scripts/projectdir.py
ncmirtools-0.5.2.data/scripts/ncmirtool.py
