Metadata-Version: 2.0
Name: ncmirtools
Version: 0.5.2
Summary: Set of commandline tools for NCMIR
Home-page: https://github.com/CRBS/ncmirtools
Author: Christopher Churas
Author-email: churas.camera@gmail.com
License: UNKNOWN
Keywords: ncmirtools
Platform: UNKNOWN
Classifier: Development Status :: 2 - Pre-Alpha
Classifier: Intended Audience :: Developers
Classifier: Natural Language :: English
Classifier: Programming Language :: Python :: 2.7
Classifier: Programming Language :: Python :: 3.4
Classifier: Programming Language :: Python :: 3.5
Classifier: Programming Language :: Python :: 3.6
Requires-Dist: argparse
Requires-Dist: configparser
Requires-Dist: pg8000
Requires-Dist: ftpretty
Requires-Dist: paramiko
Requires-Dist: requests
